ppdiffusers/__init__.py
ppdiffusers/configuration_utils.py
ppdiffusers/image_processor.py
ppdiffusers/initializer.py
ppdiffusers/optimization.py
ppdiffusers/training_utils.py
ppdiffusers/version.py
ppdiffusers/accelerate/__init__.py
ppdiffusers/accelerate/accelerator.py
ppdiffusers/accelerate/checkpointing.py
ppdiffusers/accelerate/hooks.py
ppdiffusers/accelerate/logging.py
ppdiffusers/accelerate/optimizer.py
ppdiffusers/accelerate/paddle_hooks.py
ppdiffusers/accelerate/scheduler.py
ppdiffusers/accelerate/state.py
ppdiffusers/accelerate/tracking.py
ppdiffusers/accelerate/utils/__init__.py
ppdiffusers/accelerate/utils/constants.py
ppdiffusers/accelerate/utils/dataclasses.py
ppdiffusers/accelerate/utils/environment.py
ppdiffusers/accelerate/utils/imports.py
ppdiffusers/accelerate/utils/launch.py
ppdiffusers/accelerate/utils/memory.py
ppdiffusers/accelerate/utils/modeling.py
ppdiffusers/accelerate/utils/offload.py
ppdiffusers/accelerate/utils/operations.py
ppdiffusers/accelerate/utils/other.py
ppdiffusers/accelerate/utils/random.py
ppdiffusers/accelerate/utils/rich.py
ppdiffusers/accelerate/utils/tqdm.py
ppdiffusers/accelerate/utils/versions.py
ppdiffusers/commands/__init__.py
ppdiffusers/commands/env.py
ppdiffusers/commands/fp16_safetensors.py
ppdiffusers/commands/ppdiffusers_cli.py
ppdiffusers/experimental/__init__.py
ppdiffusers/experimental/rl/__init__.py
ppdiffusers/experimental/rl/value_guided_sampling.py
ppdiffusers/loaders/__init__.py
ppdiffusers/loaders/deprecate.py
ppdiffusers/loaders/ip_adapter.py
ppdiffusers/loaders/lora.py
ppdiffusers/loaders/lora_conversion_utils.py
ppdiffusers/loaders/single_file.py
ppdiffusers/loaders/textual_inversion.py
ppdiffusers/loaders/unet.py
ppdiffusers/loaders/utils.py
ppdiffusers/models/__init__.py
ppdiffusers/models/activations.py
ppdiffusers/models/adapter.py
ppdiffusers/models/attention.py
ppdiffusers/models/attention_processor.py
ppdiffusers/models/autoencoder_asym_kl.py
ppdiffusers/models/autoencoder_kl.py
ppdiffusers-0.29.0.dist-info/LICENSE
ppdiffusers-0.29.0.dist-info/METADATA
ppdiffusers-0.29.0.dist-info/WHEEL
ppdiffusers-0.29.0.dist-info/entry_points.txt
ppdiffusers-0.29.0.dist-info/top_level.txt
ppdiffusers-0.29.0.dist-info/RECORD
