Metadata-Version: 2.1
Name: ppdiffusers
Version: 0.29.0
Summary: PPDiffusers: Diffusers toolbox implemented based on PaddlePaddle
Home-page: https://github.com/PaddlePaddle/PaddleMIX/ppdiffusers
Author: PaddleMIX Team
Author-email: paddlemix@baidu.com
License: Apache 2.0
Keywords: ppdiffusers,paddle,paddlemix
Classifier: Programming Language :: Python :: 3
Classifier: Programming Language :: Python :: 3.6
Classifier: Programming Language :: Python :: 3.7
Classifier: Programming Language :: Python :: 3.8
Classifier: Programming Language :: Python :: 3.9
Classifier: License :: OSI Approved :: Apache Software License
Classifier: Operating System :: OS Independent
Requires-Python: >=3.6
License-File: LICENSE
Requires-Dist: paddlenlp >=2.7.2
Requires-Dist: safetensors >=0.3.1
Requires-Dist: ftfy
Requires-Dist: regex
Requires-Dist: Pillow
Requires-Dist: opencv-python
Requires-Dist: av
Requires-Dist: parameterized
Requires-Dist: requests-mock
Requires-Dist: omegaconf
Requires-Dist: note-seq
Requires-Dist: urllib3 <=2.0.0
Requires-Dist: einops >=0.6.1
Requires-Dist: paddlesde
Requires-Dist: ligo-segments
Requires-Dist: huggingface-hub >=0.22.0
Requires-Dist: hf-transfer
